{"nodes": [{"id": "modules_lazydeepseekcli_local_py", "label": "lazydeepseekcli_local.py", "file_type": "code", "source_file": "modules/lazydeepseekcli_local.py", "source_location": "L1"}, {"id": "lazydeepseekcli_local_truncate_message", "label": "truncate_message()", "file_type": "code", "source_file": "modules/lazydeepseekcli_local.py", "source_location": "L29"}, {"id": "lazydeepseekcli_local_configure_logging", "label": "configure_logging()", "file_type": "code", "source_file": "modules/lazydeepseekcli_local.py", "source_location": "L34"}, {"id": "lazydeepseekcli_local_create_complex_prompt", "label": "create_complex_prompt()", "file_type": "code", "source_file": "modules/lazydeepseekcli_local.py", "source_location": "L38"}, {"id": "lazydeepseekcli_local_load_knowledge_base", "label": "load_knowledge_base()", "file_type": "code", "source_file": "modules/lazydeepseekcli_local.py", "source_location": "L86"}, {"id": "lazydeepseekcli_local_save_knowledge_base", "label": "save_knowledge_base()", "file_type": "code", "source_file": "modules/lazydeepseekcli_local.py", "source_location": "L92"}, {"id": "lazydeepseekcli_local_add_to_knowledge_base", "label": "add_to_knowledge_base()", "file_type": "code", "source_file": "modules/lazydeepseekcli_local.py", "source_location": "L96"}, {"id": "lazydeepseekcli_local_get_relevant_knowledge", "label": "get_relevant_knowledge()", "file_type": "code", "source_file": "modules/lazydeepseekcli_local.py", "source_location": "L101"}, {"id": "lazydeepseekcli_local_transform_knowledge_base", "label": "transform_knowledge_base()", "file_type": "code", "source_file": "modules/lazydeepseekcli_local.py", "source_location": "L112"}, {"id": "lazydeepseekcli_local_process_prompt_local", "label": "process_prompt_local()", "file_type": "code", "source_file": "modules/lazydeepseekcli_local.py", "source_location": "L146"}, {"id": "lazydeepseekcli_local_parse_args", "label": "parse_args()", "file_type": "code", "source_file": "modules/lazydeepseekcli_local.py", "source_location": "L189"}], "edges": [{"source": "modules_lazydeepseekcli_local_py", "target": "os", "relation": "imports", "confidence": "EXTRACTED", "source_file": "modules/lazydeepseekcli_local.py", "source_location": "L14", "weight": 1.0}, {"source": "modules_lazydeepseekcli_local_py", "target": "logging", "relation": "imports", "confidence": "EXTRACTED", "source_file": "modules/lazydeepseekcli_local.py", "source_location": "L15", "weight": 1.0}, {"source": "modules_lazydeepseekcli_local_py", "target": "json", "relation": "imports", "confidence": "EXTRACTED", "source_file": "modules/lazydeepseekcli_local.py", "source_location": "L16", "weight": 1.0}, {"source": "modules_lazydeepseekcli_local_py", "target": "requests", "relation": "imports", "confidence": "EXTRACTED", "source_file": "modules/lazydeepseekcli_local.py", "source_location": "L17", "weight": 1.0}, {"source": "modules_lazydeepseekcli_local_py", "target": "argparse", "relation": "imports", "confidence": "EXTRACTED", "source_file": "modules/lazydeepseekcli_local.py", "source_location": "L18", "weight": 1.0}, {"source": "modules_lazydeepseekcli_local_py", "target": "flask", "relation": "imports_from", "confidence": "EXTRACTED", "source_file": "modules/lazydeepseekcli_local.py", "source_location": "L19", "weight": 1.0}, {"source": "modules_lazydeepseekcli_local_py", "target": "lazydeepseekcli_local_truncate_message", "relation": "contains", "confidence": "EXTRACTED", "source_file": "modules/lazydeepseekcli_local.py", "source_location": "L29", "weight": 1.0}, {"source": "modules_lazydeepseekcli_local_py", "target": "lazydeepseekcli_local_configure_logging", "relation": "contains", "confidence": "EXTRACTED", "source_file": "modules/lazydeepseekcli_local.py", "source_location": "L34", "weight": 1.0}, {"source": "modules_lazydeepseekcli_local_py", "target": "lazydeepseekcli_local_create_complex_prompt", "relation": "contains", "confidence": "EXTRACTED", "source_file": "modules/lazydeepseekcli_local.py", "source_location": "L38", "weight": 1.0}, {"source": "modules_lazydeepseekcli_local_py", "target": "lazydeepseekcli_local_load_knowledge_base", "relation": "contains", "confidence": "EXTRACTED", "source_file": "modules/lazydeepseekcli_local.py", "source_location": "L86", "weight": 1.0}, {"source": "modules_lazydeepseekcli_local_py", "target": "lazydeepseekcli_local_save_knowledge_base", "relation": "contains", "confidence": "EXTRACTED", "source_file": "modules/lazydeepseekcli_local.py", "source_location": "L92", "weight": 1.0}, {"source": "modules_lazydeepseekcli_local_py", "target": "lazydeepseekcli_local_add_to_knowledge_base", "relation": "contains", "confidence": "EXTRACTED", "source_file": "modules/lazydeepseekcli_local.py", "source_location": "L96", "weight": 1.0}, {"source": "modules_lazydeepseekcli_local_py", "target": "lazydeepseekcli_local_get_relevant_knowledge", "relation": "contains", "confidence": "EXTRACTED", "source_file": "modules/lazydeepseekcli_local.py", "source_location": "L101", "weight": 1.0}, {"source": "modules_lazydeepseekcli_local_py", "target": "lazydeepseekcli_local_transform_knowledge_base", "relation": "contains", "confidence": "EXTRACTED", "source_file": "modules/lazydeepseekcli_local.py", "source_location": "L112", "weight": 1.0}, {"source": "modules_lazydeepseekcli_local_py", "target": "lazydeepseekcli_local_process_prompt_local", "relation": "contains", "confidence": "EXTRACTED", "source_file": "modules/lazydeepseekcli_local.py", "source_location": "L146", "weight": 1.0}, {"source": "modules_lazydeepseekcli_local_py", "target": "lazydeepseekcli_local_parse_args", "relation": "contains", "confidence": "EXTRACTED", "source_file": "modules/lazydeepseekcli_local.py", "source_location": "L189", "weight": 1.0}, {"source": "lazydeepseekcli_local_add_to_knowledge_base", "target": "lazydeepseekcli_local_load_knowledge_base", "relation": "calls", "confidence": "EXTRACTED", "source_file": "modules/lazydeepseekcli_local.py", "source_location": "L97", "weight": 1.0}, {"source": "lazydeepseekcli_local_add_to_knowledge_base", "target": "lazydeepseekcli_local_save_knowledge_base", "relation": "calls", "confidence": "EXTRACTED", "source_file": "modules/lazydeepseekcli_local.py", "source_location": "L99", "weight": 1.0}, {"source": "lazydeepseekcli_local_get_relevant_knowledge", "target": "lazydeepseekcli_local_load_knowledge_base", "relation": "calls", "confidence": "EXTRACTED", "source_file": "modules/lazydeepseekcli_local.py", "source_location": "L105", "weight": 1.0}, {"source": "lazydeepseekcli_local_transform_knowledge_base", "target": "lazydeepseekcli_local_load_knowledge_base", "relation": "calls", "confidence": "EXTRACTED", "source_file": "modules/lazydeepseekcli_local.py", "source_location": "L113", "weight": 1.0}, {"source": "lazydeepseekcli_local_transform_knowledge_base", "target": "lazydeepseekcli_local_create_complex_prompt", "relation": "calls", "confidence": "EXTRACTED", "source_file": "modules/lazydeepseekcli_local.py", "source_location": "L117", "weight": 1.0}, {"source": "lazydeepseekcli_local_transform_knowledge_base", "target": "lazydeepseekcli_local_truncate_message", "relation": "calls", "confidence": "EXTRACTED", "source_file": "modules/lazydeepseekcli_local.py", "source_location": "L117", "weight": 1.0}, {"source": "lazydeepseekcli_local_transform_knowledge_base", "target": "lazydeepseekcli_local_save_knowledge_base", "relation": "calls", "confidence": "EXTRACTED", "source_file": "modules/lazydeepseekcli_local.py", "source_location": "L143", "weight": 1.0}, {"source": "lazydeepseekcli_local_process_prompt_local", "target": "lazydeepseekcli_local_configure_logging", "relation": "calls", "confidence": "EXTRACTED", "source_file": "modules/lazydeepseekcli_local.py", "source_location": "L147", "weight": 1.0}, {"source": "lazydeepseekcli_local_process_prompt_local", "target": "lazydeepseekcli_local_get_relevant_knowledge", "relation": "calls", "confidence": "EXTRACTED", "source_file": "modules/lazydeepseekcli_local.py", "source_location": "L149", "weight": 1.0}, {"source": "lazydeepseekcli_local_process_prompt_local", "target": "lazydeepseekcli_local_create_complex_prompt", "relation": "calls", "confidence": "EXTRACTED", "source_file": "modules/lazydeepseekcli_local.py", "source_location": "L150", "weight": 1.0}], "raw_calls": [{"caller_nid": "lazydeepseekcli_local_truncate_message", "callee": "len", "source_file": "modules/lazydeepseekcli_local.py", "source_location": "L30"}, {"caller_nid": "lazydeepseekcli_local_configure_logging", "callee": "basicConfig", "source_file": "modules/lazydeepseekcli_local.py", "source_location": "L36"}, {"caller_nid": "lazydeepseekcli_local_create_complex_prompt", "callee": "open", "source_file": "modules/lazydeepseekcli_local.py", "source_location": "L39"}, {"caller_nid": "lazydeepseekcli_local_create_complex_prompt", "callee": "load", "source_file": "modules/lazydeepseekcli_local.py", "source_location": "L40"}, {"caller_nid": "lazydeepseekcli_local_create_complex_prompt", "callee": "get", "source_file": "modules/lazydeepseekcli_local.py", "source_location": "L41"}, {"caller_nid": "lazydeepseekcli_local_create_complex_prompt", "callee": "get", "source_file": "modules/lazydeepseekcli_local.py", "source_location": "L42"}, {"caller_nid": "lazydeepseekcli_local_create_complex_prompt", "callee": "get", "source_file": "modules/lazydeepseekcli_local.py", "source_location": "L43"}, {"caller_nid": "lazydeepseekcli_local_create_complex_prompt", "callee": "get", "source_file": "modules/lazydeepseekcli_local.py", "source_location": "L44"}, {"caller_nid": "lazydeepseekcli_local_create_complex_prompt", "callee": "get", "source_file": "modules/lazydeepseekcli_local.py", "source_location": "L45"}, {"caller_nid": "lazydeepseekcli_local_create_complex_prompt", "callee": "get", "source_file": "modules/lazydeepseekcli_local.py", "source_location": "L46"}, {"caller_nid": "lazydeepseekcli_local_create_complex_prompt", "callee": "get", "source_file": "modules/lazydeepseekcli_local.py", "source_location": "L47"}, {"caller_nid": "lazydeepseekcli_local_create_complex_prompt", "callee": "get", "source_file": "modules/lazydeepseekcli_local.py", "source_location": "L48"}, {"caller_nid": "lazydeepseekcli_local_load_knowledge_base", "callee": "exists", "source_file": "modules/lazydeepseekcli_local.py", "source_location": "L87"}, {"caller_nid": "lazydeepseekcli_local_load_knowledge_base", "callee": "open", "source_file": "modules/lazydeepseekcli_local.py", "source_location": "L88"}, {"caller_nid": "lazydeepseekcli_local_load_knowledge_base", "callee": "load", "source_file": "modules/lazydeepseekcli_local.py", "source_location": "L89"}, {"caller_nid": "lazydeepseekcli_local_save_knowledge_base", "callee": "open", "source_file": "modules/lazydeepseekcli_local.py", "source_location": "L93"}, {"caller_nid": "lazydeepseekcli_local_save_knowledge_base", "callee": "dump", "source_file": "modules/lazydeepseekcli_local.py", "source_location": "L94"}, {"caller_nid": "lazydeepseekcli_local_get_relevant_knowledge", "callee": "isinstance", "source_file": "modules/lazydeepseekcli_local.py", "source_location": "L102"}, {"caller_nid": "lazydeepseekcli_local_get_relevant_knowledge", "callee": "str", "source_file": "modules/lazydeepseekcli_local.py", "source_location": "L103"}, {"caller_nid": "lazydeepseekcli_local_get_relevant_knowledge", "callee": "items", "source_file": "modules/lazydeepseekcli_local.py", "source_location": "L107"}, {"caller_nid": "lazydeepseekcli_local_get_relevant_knowledge", "callee": "append", "source_file": "modules/lazydeepseekcli_local.py", "source_location": "L109"}, {"caller_nid": "lazydeepseekcli_local_get_relevant_knowledge", "callee": "join", "source_file": "modules/lazydeepseekcli_local.py", "source_location": "L110"}, {"caller_nid": "lazydeepseekcli_local_transform_knowledge_base", "callee": "items", "source_file": "modules/lazydeepseekcli_local.py", "source_location": "L115"}, {"caller_nid": "lazydeepseekcli_local_transform_knowledge_base", "callee": "join", "source_file": "modules/lazydeepseekcli_local.py", "source_location": "L117"}, {"caller_nid": "lazydeepseekcli_local_transform_knowledge_base", "callee": "post", "source_file": "modules/lazydeepseekcli_local.py", "source_location": "L119"}, {"caller_nid": "lazydeepseekcli_local_transform_knowledge_base", "callee": "iter_lines", "source_file": "modules/lazydeepseekcli_local.py", "source_location": "L128"}, {"caller_nid": "lazydeepseekcli_local_transform_knowledge_base", "callee": "loads", "source_file": "modules/lazydeepseekcli_local.py", "source_location": "L131"}, {"caller_nid": "lazydeepseekcli_local_transform_knowledge_base", "callee": "decode", "source_file": "modules/lazydeepseekcli_local.py", "source_location": "L131"}, {"caller_nid": "lazydeepseekcli_local_transform_knowledge_base", "callee": "print", "source_file": "modules/lazydeepseekcli_local.py", "source_location": "L132"}, {"caller_nid": "lazydeepseekcli_local_transform_knowledge_base", "callee": "get", "source_file": "modules/lazydeepseekcli_local.py", "source_location": "L132"}, {"caller_nid": "lazydeepseekcli_local_transform_knowledge_base", "callee": "print", "source_file": "modules/lazydeepseekcli_local.py", "source_location": "L134"}, {"caller_nid": "lazydeepseekcli_local_transform_knowledge_base", "callee": "print", "source_file": "modules/lazydeepseekcli_local.py", "source_location": "L135"}, {"caller_nid": "lazydeepseekcli_local_transform_knowledge_base", "callee": "error", "source_file": "modules/lazydeepseekcli_local.py", "source_location": "L137"}, {"caller_nid": "lazydeepseekcli_local_transform_knowledge_base", "callee": "error", "source_file": "modules/lazydeepseekcli_local.py", "source_location": "L140"}, {"caller_nid": "lazydeepseekcli_local_transform_knowledge_base", "callee": "print", "source_file": "modules/lazydeepseekcli_local.py", "source_location": "L144"}, {"caller_nid": "lazydeepseekcli_local_process_prompt_local", "callee": "join", "source_file": "modules/lazydeepseekcli_local.py", "source_location": "L150"}, {"caller_nid": "lazydeepseekcli_local_process_prompt_local", "callee": "post", "source_file": "modules/lazydeepseekcli_local.py", "source_location": "L153"}, {"caller_nid": "lazydeepseekcli_local_process_prompt_local", "callee": "Response", "source_file": "modules/lazydeepseekcli_local.py", "source_location": "L181"}, {"caller_nid": "lazydeepseekcli_local_process_prompt_local", "callee": "stream_with_context", "source_file": "modules/lazydeepseekcli_local.py", "source_location": "L181"}, {"caller_nid": "lazydeepseekcli_local_process_prompt_local", "callee": "generate", "source_file": "modules/lazydeepseekcli_local.py", "source_location": "L181"}, {"caller_nid": "lazydeepseekcli_local_process_prompt_local", "callee": "jsonify", "source_file": "modules/lazydeepseekcli_local.py", "source_location": "L183"}, {"caller_nid": "lazydeepseekcli_local_process_prompt_local", "callee": "jsonify", "source_file": "modules/lazydeepseekcli_local.py", "source_location": "L186"}, {"caller_nid": "lazydeepseekcli_local_process_prompt_local", "callee": "str", "source_file": "modules/lazydeepseekcli_local.py", "source_location": "L186"}, {"caller_nid": "lazydeepseekcli_local_parse_args", "callee": "ArgumentParser", "source_file": "modules/lazydeepseekcli_local.py", "source_location": "L190"}, {"caller_nid": "lazydeepseekcli_local_parse_args", "callee": "add_argument", "source_file": "modules/lazydeepseekcli_local.py", "source_location": "L191"}, {"caller_nid": "lazydeepseekcli_local_parse_args", "callee": "add_argument", "source_file": "modules/lazydeepseekcli_local.py", "source_location": "L192"}, {"caller_nid": "lazydeepseekcli_local_parse_args", "callee": "add_argument", "source_file": "modules/lazydeepseekcli_local.py", "source_location": "L193"}, {"caller_nid": "lazydeepseekcli_local_parse_args", "callee": "add_argument", "source_file": "modules/lazydeepseekcli_local.py", "source_location": "L194"}]}