{"nodes": [{"id": "modules_lazykeygen_py", "label": "lazykeygen.py", "file_type": "code", "source_file": "modules/lazykeygen.py", "source_location": "L1"}, {"id": "lazykeygen_pad", "label": "pad()", "file_type": "code", "source_file": "modules/lazykeygen.py", "source_location": "L6"}, {"id": "lazykeygen_encrypt", "label": "encrypt()", "file_type": "code", "source_file": "modules/lazykeygen.py", "source_location": "L9"}, {"id": "lazykeygen_decrypt", "label": "decrypt()", "file_type": "code", "source_file": "modules/lazykeygen.py", "source_location": "L15"}, {"id": "lazykeygen_generate_key", "label": "generate_key()", "file_type": "code", "source_file": "modules/lazykeygen.py", "source_location": "L21"}, {"id": "lazykeygen_main", "label": "main()", "file_type": "code", "source_file": "modules/lazykeygen.py", "source_location": "L24"}], "edges": [{"source": "modules_lazykeygen_py", "target": "argparse", "relation": "imports", "confidence": "EXTRACTED", "source_file": "modules/lazykeygen.py", "source_location": "L1", "weight": 1.0}, {"source": "modules_lazykeygen_py", "target": "binascii", "relation": "imports", "confidence": "EXTRACTED", "source_file": "modules/lazykeygen.py", "source_location": "L2", "weight": 1.0}, {"source": "modules_lazykeygen_py", "target": "crypto_cipher", "relation": "imports_from", "confidence": "EXTRACTED", "source_file": "modules/lazykeygen.py", "source_location": "L3", "weight": 1.0}, {"source": "modules_lazykeygen_py", "target": "crypto_random", "relation": "imports_from", "confidence": "EXTRACTED", "source_file": "modules/lazykeygen.py", "source_location": "L4", "weight": 1.0}, {"source": "modules_lazykeygen_py", "target": "lazykeygen_pad", "relation": "contains", "confidence": "EXTRACTED", "source_file": "modules/lazykeygen.py", "source_location": "L6", "weight": 1.0}, {"source": "modules_lazykeygen_py", "target": "lazykeygen_encrypt", "relation": "contains", "confidence": "EXTRACTED", "source_file": "modules/lazykeygen.py", "source_location": "L9", "weight": 1.0}, {"source": "modules_lazykeygen_py", "target": "lazykeygen_decrypt", "relation": "contains", "confidence": "EXTRACTED", "source_file": "modules/lazykeygen.py", "source_location": "L15", "weight": 1.0}, {"source": "modules_lazykeygen_py", "target": "lazykeygen_generate_key", "relation": "contains", "confidence": "EXTRACTED", "source_file": "modules/lazykeygen.py", "source_location": "L21", "weight": 1.0}, {"source": "modules_lazykeygen_py", "target": "lazykeygen_main", "relation": "contains", "confidence": "EXTRACTED", "source_file": "modules/lazykeygen.py", "source_location": "L24", "weight": 1.0}, {"source": "lazykeygen_encrypt", "target": "lazykeygen_pad", "relation": "calls", "confidence": "EXTRACTED", "source_file": "modules/lazykeygen.py", "source_location": "L10", "weight": 1.0}, {"source": "lazykeygen_main", "target": "lazykeygen_generate_key", "relation": "calls", "confidence": "EXTRACTED", "source_file": "modules/lazykeygen.py", "source_location": "L29", "weight": 1.0}, {"source": "lazykeygen_main", "target": "lazykeygen_encrypt", "relation": "calls", "confidence": "EXTRACTED", "source_file": "modules/lazykeygen.py", "source_location": "L33", "weight": 1.0}, {"source": "lazykeygen_main", "target": "lazykeygen_decrypt", "relation": "calls", "confidence": "EXTRACTED", "source_file": "modules/lazykeygen.py", "source_location": "L36", "weight": 1.0}], "raw_calls": [{"caller_nid": "lazykeygen_pad", "callee": "len", "source_file": "modules/lazykeygen.py", "source_location": "L7"}, {"caller_nid": "lazykeygen_encrypt", "callee": "get_random_bytes", "source_file": "modules/lazykeygen.py", "source_location": "L11"}, {"caller_nid": "lazykeygen_encrypt", "callee": "new", "source_file": "modules/lazykeygen.py", "source_location": "L12"}, {"caller_nid": "lazykeygen_decrypt", "callee": "new", "source_file": "modules/lazykeygen.py", "source_location": "L17"}, {"caller_nid": "lazykeygen_decrypt", "callee": "rstrip", "source_file": "modules/lazykeygen.py", "source_location": "L19"}, {"caller_nid": "lazykeygen_generate_key", "callee": "get_random_bytes", "source_file": "modules/lazykeygen.py", "source_location": "L22"}, {"caller_nid": "lazykeygen_main", "callee": "ArgumentParser", "source_file": "modules/lazykeygen.py", "source_location": "L25"}, {"caller_nid": "lazykeygen_main", "callee": "add_argument", "source_file": "modules/lazykeygen.py", "source_location": "L26"}, {"caller_nid": "lazykeygen_main", "callee": "parse_args", "source_file": "modules/lazykeygen.py", "source_location": "L27"}, {"caller_nid": "lazykeygen_main", "callee": "print", "source_file": "modules/lazykeygen.py", "source_location": "L30"}, {"caller_nid": "lazykeygen_main", "callee": "decode", "source_file": "modules/lazykeygen.py", "source_location": "L30"}, {"caller_nid": "lazykeygen_main", "callee": "hexlify", "source_file": "modules/lazykeygen.py", "source_location": "L30"}, {"caller_nid": "lazykeygen_main", "callee": "encode", "source_file": "modules/lazykeygen.py", "source_location": "L32"}, {"caller_nid": "lazykeygen_main", "callee": "print", "source_file": "modules/lazykeygen.py", "source_location": "L34"}, {"caller_nid": "lazykeygen_main", "callee": "decode", "source_file": "modules/lazykeygen.py", "source_location": "L34"}, {"caller_nid": "lazykeygen_main", "callee": "hexlify", "source_file": "modules/lazykeygen.py", "source_location": "L34"}, {"caller_nid": "lazykeygen_main", "callee": "print", "source_file": "modules/lazykeygen.py", "source_location": "L37"}, {"caller_nid": "lazykeygen_main", "callee": "decode", "source_file": "modules/lazykeygen.py", "source_location": "L37"}]}