{"nodes": [{"id": "modules_apt_playbooks_py", "label": "apt_playbooks.py", "file_type": "code", "source_file": "modules/apt_playbooks.py", "source_location": "L1"}, {"id": "apt_playbooks_atomictestref", "label": "AtomicTestRef", "file_type": "code", "source_file": "modules/apt_playbooks.py", "source_location": "L42"}, {"id": "apt_playbooks_calderaabilityref", "label": "CalderaAbilityRef", "file_type": "code", "source_file": "modules/apt_playbooks.py", "source_location": "L49"}, {"id": "apt_playbooks_phasestep", "label": "PhaseStep", "file_type": "code", "source_file": "modules/apt_playbooks.py", "source_location": "L55"}, {"id": "apt_playbooks_aptplaybook", "label": "AptPlaybook", "file_type": "code", "source_file": "modules/apt_playbooks.py", "source_location": "L66"}, {"id": "apt_playbooks_from_dict", "label": "from_dict()", "file_type": "code", "source_file": "modules/apt_playbooks.py", "source_location": "L75"}, {"id": "apt_playbooks_aptplaybook_to_summary", "label": ".to_summary()", "file_type": "code", "source_file": "modules/apt_playbooks.py", "source_location": "L102"}, {"id": "apt_playbooks_aptplaybookengine", "label": "AptPlaybookEngine", "file_type": "code", "source_file": "modules/apt_playbooks.py", "source_location": "L114"}, {"id": "apt_playbooks_aptplaybookengine_init", "label": ".__init__()", "file_type": "code", "source_file": "modules/apt_playbooks.py", "source_location": "L117"}, {"id": "apt_playbooks_aptplaybookengine_load_all", "label": "._load_all()", "file_type": "code", "source_file": "modules/apt_playbooks.py", "source_location": "L122"}, {"id": "apt_playbooks_aptplaybookengine_list_playbooks", "label": ".list_playbooks()", "file_type": "code", "source_file": "modules/apt_playbooks.py", "source_location": "L134"}, {"id": "apt_playbooks_aptplaybookengine_get", "label": ".get()", "file_type": "code", "source_file": "modules/apt_playbooks.py", "source_location": "L137"}, {"id": "apt_playbooks_aptplaybookengine_validate", "label": ".validate()", "file_type": "code", "source_file": "modules/apt_playbooks.py", "source_location": "L141"}, {"id": "apt_playbooks_aptplaybookengine_build_atomic_index", "label": "._build_atomic_index()", "file_type": "code", "source_file": "modules/apt_playbooks.py", "source_location": "L174"}, {"id": "apt_playbooks_aptplaybookengine_generate_attack_plan", "label": ".generate_attack_plan()", "file_type": "code", "source_file": "modules/apt_playbooks.py", "source_location": "L188"}, {"id": "apt_playbooks_aptplaybookengine_report_json", "label": ".report_json()", "file_type": "code", "source_file": "modules/apt_playbooks.py", "source_location": "L203"}, {"id": "apt_playbooks_rationale_1", "label": "APT Playbook Engine \u2014 map public APT reports to executable Atomic Red Team chain", "file_type": "rationale", "source_file": "modules/apt_playbooks.py", "source_location": "L1"}, {"id": "apt_playbooks_rationale_115", "label": "Load, list, validate and execute APT playbooks.", "file_type": "rationale", "source_file": "modules/apt_playbooks.py", "source_location": "L115"}, {"id": "apt_playbooks_rationale_142", "label": "Validate that all referenced atomic tests exist locally.", "file_type": "rationale", "source_file": "modules/apt_playbooks.py", "source_location": "L142"}, {"id": "apt_playbooks_rationale_189", "label": "Generate a legacy ``attack_plan.yaml`` from an enriched APT playbook.", "file_type": "rationale", "source_file": "modules/apt_playbooks.py", "source_location": "L189"}, {"id": "apt_playbooks_rationale_204", "label": "Write a structured JSON report of the playbook for the operator.", "file_type": "rationale", "source_file": "modules/apt_playbooks.py", "source_location": "L204"}], "edges": [{"source": "modules_apt_playbooks_py", "target": "glob", "relation": "imports", "confidence": "EXTRACTED", "source_file": "modules/apt_playbooks.py", "source_location": "L28", "weight": 1.0}, {"source": "modules_apt_playbooks_py", "target": "json", "relation": "imports", "confidence": "EXTRACTED", "source_file": "modules/apt_playbooks.py", "source_location": "L29", "weight": 1.0}, {"source": "modules_apt_playbooks_py", "target": "os", "relation": "imports", "confidence": "EXTRACTED", "source_file": "modules/apt_playbooks.py", "source_location": "L30", "weight": 1.0}, {"source": "modules_apt_playbooks_py", "target": "time", "relation": "imports", "confidence": "EXTRACTED", "source_file": "modules/apt_playbooks.py", "source_location": "L31", "weight": 1.0}, {"source": "modules_apt_playbooks_py", "target": "dataclasses", "relation": "imports_from", "confidence": "EXTRACTED", "source_file": "modules/apt_playbooks.py", "source_location": "L32", "weight": 1.0}, {"source": "modules_apt_playbooks_py", "target": "typing", "relation": "imports_from", "confidence": "EXTRACTED", "source_file": "modules/apt_playbooks.py", "source_location": "L33", "weight": 1.0}, {"source": "modules_apt_playbooks_py", "target": "yaml", "relation": "imports", "confidence": "EXTRACTED", "source_file": "modules/apt_playbooks.py", "source_location": "L35", "weight": 1.0}, {"source": "modules_apt_playbooks_py", "target": "core_console", "relation": "imports_from", "confidence": "EXTRACTED", "source_file": "modules/apt_playbooks.py", "source_location": "L37", "weight": 1.0}, {"source": "modules_apt_playbooks_py", "target": "utils", "relation": "imports_from", "confidence": "EXTRACTED", "source_file": "modules/apt_playbooks.py", "source_location": "L38", "weight": 1.0}, {"source": "modules_apt_playbooks_py", "target": "apt_playbooks_atomictestref", "relation": "contains", "confidence": "EXTRACTED", "source_file": "modules/apt_playbooks.py", "source_location": "L42", "weight": 1.0}, {"source": "modules_apt_playbooks_py", "target": "apt_playbooks_calderaabilityref", "relation": "contains", "confidence": "EXTRACTED", "source_file": "modules/apt_playbooks.py", "source_location": "L49", "weight": 1.0}, {"source": "modules_apt_playbooks_py", "target": "apt_playbooks_phasestep", "relation": "contains", "confidence": "EXTRACTED", "source_file": "modules/apt_playbooks.py", "source_location": "L55", "weight": 1.0}, {"source": "modules_apt_playbooks_py", "target": "apt_playbooks_aptplaybook", "relation": "contains", "confidence": "EXTRACTED", "source_file": "modules/apt_playbooks.py", "source_location": "L66", "weight": 1.0}, {"source": "modules_apt_playbooks_py", "target": "apt_playbooks_from_dict", "relation": "contains", "confidence": "EXTRACTED", "source_file": "modules/apt_playbooks.py", "source_location": "L75", "weight": 1.0}, {"source": "apt_playbooks_aptplaybook", "target": "apt_playbooks_aptplaybook_to_summary", "relation": "method", "confidence": "EXTRACTED", "source_file": "modules/apt_playbooks.py", "source_location": "L102", "weight": 1.0}, {"source": "modules_apt_playbooks_py", "target": "apt_playbooks_aptplaybookengine", "relation": "contains", "confidence": "EXTRACTED", "source_file": "modules/apt_playbooks.py", "source_location": "L114", "weight": 1.0}, {"source": "apt_playbooks_aptplaybookengine", "target": "apt_playbooks_aptplaybookengine_init", "relation": "method", "confidence": "EXTRACTED", "source_file": "modules/apt_playbooks.py", "source_location": "L117", "weight": 1.0}, {"source": "apt_playbooks_aptplaybookengine", "target": "apt_playbooks_aptplaybookengine_load_all", "relation": "method", "confidence": "EXTRACTED", "source_file": "modules/apt_playbooks.py", "source_location": "L122", "weight": 1.0}, {"source": "apt_playbooks_aptplaybookengine", "target": "apt_playbooks_aptplaybookengine_list_playbooks", "relation": "method", "confidence": "EXTRACTED", "source_file": "modules/apt_playbooks.py", "source_location": "L134", "weight": 1.0}, {"source": "apt_playbooks_aptplaybookengine", "target": "apt_playbooks_aptplaybookengine_get", "relation": "method", "confidence": "EXTRACTED", "source_file": "modules/apt_playbooks.py", "source_location": "L137", "weight": 1.0}, {"source": "apt_playbooks_aptplaybookengine", "target": "apt_playbooks_aptplaybookengine_validate", "relation": "method", "confidence": "EXTRACTED", "source_file": "modules/apt_playbooks.py", "source_location": "L141", "weight": 1.0}, {"source": "apt_playbooks_aptplaybookengine", "target": "apt_playbooks_aptplaybookengine_build_atomic_index", "relation": "method", "confidence": "EXTRACTED", "source_file": "modules/apt_playbooks.py", "source_location": "L174", "weight": 1.0}, {"source": "apt_playbooks_aptplaybookengine", "target": "apt_playbooks_aptplaybookengine_generate_attack_plan", "relation": "method", "confidence": "EXTRACTED", "source_file": "modules/apt_playbooks.py", "source_location": "L188", "weight": 1.0}, {"source": "apt_playbooks_aptplaybookengine", "target": "apt_playbooks_aptplaybookengine_report_json", "relation": "method", "confidence": "EXTRACTED", "source_file": "modules/apt_playbooks.py", "source_location": "L203", "weight": 1.0}, {"source": "apt_playbooks_from_dict", "target": "apt_playbooks_aptplaybookengine_get", "relation": "calls", "confidence": "EXTRACTED", "source_file": "modules/apt_playbooks.py", "source_location": "L77", "weight": 1.0}, {"source": "apt_playbooks_from_dict", "target": "apt_playbooks_atomictestref", "relation": "calls", "confidence": "EXTRACTED", "source_file": "modules/apt_playbooks.py", "source_location": "L79", "weight": 1.0}, {"source": "apt_playbooks_from_dict", "target": "apt_playbooks_calderaabilityref", "relation": "calls", "confidence": "EXTRACTED", "source_file": "modules/apt_playbooks.py", "source_location": "L82", "weight": 1.0}, {"source": "apt_playbooks_from_dict", "target": "apt_playbooks_phasestep", "relation": "calls", "confidence": "EXTRACTED", "source_file": "modules/apt_playbooks.py", "source_location": "L84", "weight": 1.0}, {"source": "apt_playbooks_aptplaybookengine_init", "target": "apt_playbooks_aptplaybookengine_load_all", "relation": "calls", "confidence": "EXTRACTED", "source_file": "modules/apt_playbooks.py", "source_location": "L120", "weight": 1.0}, {"source": "apt_playbooks_aptplaybookengine_load_all", "target": "apt_playbooks_from_dict", "relation": "calls", "confidence": "EXTRACTED", "source_file": "modules/apt_playbooks.py", "source_location": "L128", "weight": 1.0}, {"source": "apt_playbooks_aptplaybookengine_list_playbooks", "target": "apt_playbooks_aptplaybook_to_summary", "relation": "calls", "confidence": "EXTRACTED", "source_file": "modules/apt_playbooks.py", "source_location": "L135", "weight": 1.0}, {"source": "apt_playbooks_aptplaybookengine_validate", "target": "apt_playbooks_aptplaybookengine_build_atomic_index", "relation": "calls", "confidence": "EXTRACTED", "source_file": "modules/apt_playbooks.py", "source_location": "L146", "weight": 1.0}, {"source": "apt_playbooks_rationale_1", "target": "modules_apt_playbooks_py", "relation": "rationale_for", "confidence": "EXTRACTED", "source_file": "modules/apt_playbooks.py", "source_location": "L1", "weight": 1.0}, {"source": "apt_playbooks_rationale_115", "target": "apt_playbooks_aptplaybookengine", "relation": "rationale_for", "confidence": "EXTRACTED", "source_file": "modules/apt_playbooks.py", "source_location": "L115", "weight": 1.0}, {"source": "apt_playbooks_rationale_142", "target": "apt_playbooks_aptplaybookengine_validate", "relation": "rationale_for", "confidence": "EXTRACTED", "source_file": "modules/apt_playbooks.py", "source_location": "L142", "weight": 1.0}, {"source": "apt_playbooks_rationale_189", "target": "apt_playbooks_aptplaybookengine_generate_attack_plan", "relation": "rationale_for", "confidence": "EXTRACTED", "source_file": "modules/apt_playbooks.py", "source_location": "L189", "weight": 1.0}, {"source": "apt_playbooks_rationale_204", "target": "apt_playbooks_aptplaybookengine_report_json", "relation": "rationale_for", "confidence": "EXTRACTED", "source_file": "modules/apt_playbooks.py", "source_location": "L204", "weight": 1.0}], "raw_calls": [{"caller_nid": "apt_playbooks_from_dict", "callee": "append", "source_file": "modules/apt_playbooks.py", "source_location": "L84"}, {"caller_nid": "apt_playbooks_from_dict", "callee": "cls", "source_file": "modules/apt_playbooks.py", "source_location": "L93"}, {"caller_nid": "apt_playbooks_aptplaybook_to_summary", "callee": "len", "source_file": "modules/apt_playbooks.py", "source_location": "L108"}, {"caller_nid": "apt_playbooks_aptplaybook_to_summary", "callee": "sum", "source_file": "modules/apt_playbooks.py", "source_location": "L109"}, {"caller_nid": "apt_playbooks_aptplaybook_to_summary", "callee": "len", "source_file": "modules/apt_playbooks.py", "source_location": "L109"}, {"caller_nid": "apt_playbooks_aptplaybook_to_summary", "callee": "sum", "source_file": "modules/apt_playbooks.py", "source_location": "L110"}, {"caller_nid": "apt_playbooks_aptplaybook_to_summary", "callee": "len", "source_file": "modules/apt_playbooks.py", "source_location": "L110"}, {"caller_nid": "apt_playbooks_aptplaybookengine_load_all", "callee": "join", "source_file": "modules/apt_playbooks.py", "source_location": "L123"}, {"caller_nid": "apt_playbooks_aptplaybookengine_load_all", "callee": "glob", "source_file": "modules/apt_playbooks.py", "source_location": "L124"}, {"caller_nid": "apt_playbooks_aptplaybookengine_load_all", "callee": "open", "source_file": "modules/apt_playbooks.py", "source_location": "L126"}, {"caller_nid": "apt_playbooks_aptplaybookengine_load_all", "callee": "safe_load", "source_file": "modules/apt_playbooks.py", "source_location": "L127"}, {"caller_nid": "apt_playbooks_aptplaybookengine_load_all", "callee": "replace", "source_file": "modules/apt_playbooks.py", "source_location": "L129"}, {"caller_nid": "apt_playbooks_aptplaybookengine_load_all", "callee": "lower", "source_file": "modules/apt_playbooks.py", "source_location": "L129"}, {"caller_nid": "apt_playbooks_aptplaybookengine_load_all", "callee": "print_warn", "source_file": "modules/apt_playbooks.py", "source_location": "L132"}, {"caller_nid": "apt_playbooks_aptplaybookengine_list_playbooks", "callee": "values", "source_file": "modules/apt_playbooks.py", "source_location": "L135"}, {"caller_nid": "apt_playbooks_aptplaybookengine_get", "callee": "replace", "source_file": "modules/apt_playbooks.py", "source_location": "L138"}, {"caller_nid": "apt_playbooks_aptplaybookengine_get", "callee": "lower", "source_file": "modules/apt_playbooks.py", "source_location": "L138"}, {"caller_nid": "apt_playbooks_aptplaybookengine_validate", "callee": "exists", "source_file": "modules/apt_playbooks.py", "source_location": "L145"}, {"caller_nid": "apt_playbooks_aptplaybookengine_validate", "callee": "append", "source_file": "modules/apt_playbooks.py", "source_location": "L153"}, {"caller_nid": "apt_playbooks_aptplaybookengine_validate", "callee": "append", "source_file": "modules/apt_playbooks.py", "source_location": "L159"}, {"caller_nid": "apt_playbooks_aptplaybookengine_validate", "callee": "len", "source_file": "modules/apt_playbooks.py", "source_location": "L167"}, {"caller_nid": "apt_playbooks_aptplaybookengine_validate", "callee": "len", "source_file": "modules/apt_playbooks.py", "source_location": "L168"}, {"caller_nid": "apt_playbooks_aptplaybookengine_validate", "callee": "len", "source_file": "modules/apt_playbooks.py", "source_location": "L169"}, {"caller_nid": "apt_playbooks_aptplaybookengine_build_atomic_index", "callee": "glob", "source_file": "modules/apt_playbooks.py", "source_location": "L176"}, {"caller_nid": "apt_playbooks_aptplaybookengine_build_atomic_index", "callee": "join", "source_file": "modules/apt_playbooks.py", "source_location": "L176"}, {"caller_nid": "apt_playbooks_aptplaybookengine_build_atomic_index", "callee": "open", "source_file": "modules/apt_playbooks.py", "source_location": "L179"}, {"caller_nid": "apt_playbooks_aptplaybookengine_build_atomic_index", "callee": "safe_load", "source_file": "modules/apt_playbooks.py", "source_location": "L180"}, {"caller_nid": "apt_playbooks_aptplaybookengine_generate_attack_plan", "callee": "append", "source_file": "modules/apt_playbooks.py", "source_location": "L193"}, {"caller_nid": "apt_playbooks_aptplaybookengine_generate_attack_plan", "callee": "open", "source_file": "modules/apt_playbooks.py", "source_location": "L199"}, {"caller_nid": "apt_playbooks_aptplaybookengine_generate_attack_plan", "callee": "dump", "source_file": "modules/apt_playbooks.py", "source_location": "L200"}, {"caller_nid": "apt_playbooks_aptplaybookengine_generate_attack_plan", "callee": "print_succ", "source_file": "modules/apt_playbooks.py", "source_location": "L201"}, {"caller_nid": "apt_playbooks_aptplaybookengine_report_json", "callee": "strftime", "source_file": "modules/apt_playbooks.py", "source_location": "L211"}, {"caller_nid": "apt_playbooks_aptplaybookengine_report_json", "callee": "open", "source_file": "modules/apt_playbooks.py", "source_location": "L231"}, {"caller_nid": "apt_playbooks_aptplaybookengine_report_json", "callee": "dump", "source_file": "modules/apt_playbooks.py", "source_location": "L232"}, {"caller_nid": "apt_playbooks_aptplaybookengine_report_json", "callee": "print_succ", "source_file": "modules/apt_playbooks.py", "source_location": "L233"}]}